claude_agent_toolkit/__init__.py
claude_agent_toolkit/constants.py
claude_agent_toolkit/exceptions.py
claude_agent_toolkit/logging.py
claude_agent_toolkit/py.typed
claude_agent_toolkit/agent/__init__.py
claude_agent_toolkit/agent/core.py
claude_agent_toolkit/agent/response_handler.py
claude_agent_toolkit/agent/tool_connector.py
claude_agent_toolkit/agent/executor/__init__.py
claude_agent_toolkit/agent/executor/base.py
claude_agent_toolkit/agent/executor/docker.py
claude_agent_toolkit/agent/executor/subprocess.py
claude_agent_toolkit/tool/__init__.py
claude_agent_toolkit/tool/abstract.py
claude_agent_toolkit/tool/base.py
claude_agent_toolkit/tool/decorator.py
claude_agent_toolkit/tool/mcp.py
claude_agent_toolkit/tool/server.py
claude_agent_toolkit/tool/utils.py
claude_agent_toolkit/tool/worker.py
claude_agent_toolkit/tools/__init__.py
claude_agent_toolkit/tools/datatransfer.py
claude_agent_toolkit/tools/filesystem.py
claude_agent_toolkit-0.2.6.dist-info/METADATA
claude_agent_toolkit-0.2.6.dist-info/WHEEL
claude_agent_toolkit-0.2.6.dist-info/licenses/LICENSE
claude_agent_toolkit-0.2.6.dist-info/RECORD
