Metadata-Version: 2.4
Name: claude-agent-toolkit
Version: 0.2.6
Summary: Python framework for building Claude Code agents with custom tools
Project-URL: Homepage, https://github.com/cheolwanpark/claude-agent-toolkit
Project-URL: Repository, https://github.com/cheolwanpark/claude-agent-toolkit.git
Project-URL: Issues, https://github.com/cheolwanpark/claude-agent-toolkit/issues
Project-URL: Changelog, https://github.com/cheolwanpark/claude-agent-toolkit/blob/main/CHANGELOG.md
Project-URL: Documentation, https://github.com/cheolwanpark/claude-agent-toolkit#readme
Project-URL: Claude Code, https://claude.ai/code
Author-email: Cheolwan Park <cheolwan.park552@gmail.com>
Maintainer-email: Cheolwan Park <cheolwan.park552@gmail.com>
License: MIT
License-File: LICENSE
Keywords: agent-framework,ai-agents,claude-agent-sdk,claude-agent-toolkit,claude-agents,claude-code,docker,mcp-tools,model-context-protocol
Classifier: Development Status :: 4 - Beta
Classifier: Intended Audience :: Developers
Classifier: License :: OSI Approved :: MIT License
Classifier: Operating System :: OS Independent
Classifier: Programming Language :: Python :: 3
Classifier: Programming Language :: Python :: 3.12
Classifier: Programming Language :: Python :: 3.13
Classifier: Topic :: Scientific/Engineering :: Artificial Intelligence
Classifier: Topic :: Software Development :: Libraries :: Application Frameworks
Classifier: Topic :: Software Development :: Libraries :: Python Modules
Classifier: Typing :: Typed
Requires-Python: >=3.12
Requires-Dist: claude-agent-sdk>=0.1.3
Requires-Dist: docker>=7.1.0
Requires-Dist: fastmcp>=2.12.2
Requires-Dist: httpx>=0.28.1
Requires-Dist: jsonpatch>=1.33
Requires-Dist: mcp>=1.3.0
Requires-Dist: uvicorn>=0.35.0
Provides-Extra: build
Requires-Dist: build>=1.0.0; extra == 'build'
Requires-Dist: check-manifest>=0.49; extra == 'build'
Requires-Dist: twine>=4.0.0; extra == 'build'
Provides-Extra: dev
Requires-Dist: black>=23.0.0; extra == 'dev'
Requires-Dist: isort>=5.12.0; extra == 'dev'
Requires-Dist: mypy>=1.5.0; extra == 'dev'
Requires-Dist: pytest-asyncio>=0.23.0; extra == 'dev'
Requires-Dist: pytest-cov>=4.0.0; extra == 'dev'
Requires-Dist: pytest>=7.0.0; extra == 'dev'
Requires-Dist: ruff>=0.1.0; extra == 'dev'
Provides-Extra: docs
Requires-Dist: myst-parser>=2.0.0; extra == 'docs'
Requires-Dist: sphinx-rtd-theme>=1.3.0; extra == 'docs'
Requires-Dist: sphinx>=7.0.0; extra == 'docs'
Provides-Extra: examples
Requires-Dist: pytz>=2023.3; extra == 'examples'
Provides-Extra: test
Requires-Dist: pytest-asyncio>=0.23.0; extra == 'test'
Requires-Dist: pytest-cov>=4.0.0; extra == 'test'
Requires-Dist: pytest-mock>=3.12.0; extra == 'test'
Requires-Dist: pytest>=7.0.0; extra == 'test'
